junior/__init__.py
junior/api.py
junior/assets.py
junior/auth.py
junior/cache.py
junior/cli.py
junior/components.py
junior/config.py
junior/context.py
junior/controls.py
junior/db.py
junior/environments.py
junior/errors.py
junior/filters.py
junior/mail.py
junior/queue.py
junior/queues.py
junior/socket.py
junior/sockets.py
junior/static.py
junior/templates.py
junior/util.py
junior/web.py
junior/config/babel.yaml
junior/config/postcss.yaml
junior/migrations/script.py.mako
junior/scripts/junior.js
junior/templates/error.haml
junior/templates/index.haml
junior/templates/layout.haml
junior-0.5.0.dist-info/LICENSE.md
junior-0.5.0.dist-info/METADATA
junior-0.5.0.dist-info/WHEEL
junior-0.5.0.dist-info/entry_points.txt
junior-0.5.0.dist-info/top_level.txt
junior-0.5.0.dist-info/RECORD
